symba/py.typed
symba/base.py
symba/__init__.py
symba/_symba.cpython-39-aarch64-linux-gnu.so
symba/_symba.pyi
symba/core/constant.py
symba/core/term.py
symba/core/__init__.py
symba/core/expression.py
symba/core/utils.py
symba/core/hints.py
symba/core/form.py
symba/core/context.py
symba-2.2.1.dist-info/RECORD
symba-2.2.1.dist-info/WHEEL
symba-2.2.1.dist-info/top_level.txt
symba-2.2.1.dist-info/LICENSE
symba-2.2.1.dist-info/METADATA
