Metadata-Version: 2.1
Name: symba
Version: 2.2.1
Home-page: https://github.com/lycantropos/symba/
Download-URL: https://github.com/lycantropos/symba/archive/master.zip
Author-email: Azat Ibrakov <azatibrakov@gmail.com>
License: MIT License
Classifier: License :: OSI Approved :: MIT License
Classifier: Programming Language :: Python :: 3.7
Classifier: Programming Language :: Python :: 3.8
Classifier: Programming Language :: Python :: 3.9
Classifier: Programming Language :: Python :: 3.10
Classifier: Programming Language :: Python :: 3.11
Classifier: Programming Language :: Python :: Implementation :: CPython
Classifier: Programming Language :: Python :: Implementation :: PyPy
Requires-Python: >=3.7
License-File: LICENSE
Requires-Dist: cfractions (<3.0.0,>=2.2.0)
Requires-Dist: reprit (<1.0,>=0.8.0)
Provides-Extra: tests
Requires-Dist: hypothesis (<7.0,>=6.70.1) ; extra == 'tests'
Requires-Dist: pytest (<8.0,>=7.2.2) ; extra == 'tests'
